{
  "$schema": "https://json.schemastore.org/tsconfig",
  "compilerOptions": {
    "allowJs": true,
    "esModuleInterop": true,
    "forceConsistentCasingInFileNames": true,
    "isolatedModules": true,
    "lib": ["DOM", "DOM.Iterable", "ESNext"],
    "module": "ESNext",
    "moduleDetection": "force",
    "moduleResolution": "bundler",
    "noEmit": true,
    "noUncheckedIndexedAccess": true,
    "resolveJsonModule": true,
    "skipLibCheck": true,
    "strict": true,
    "target": "ESNext"
  },
  "display": "Base configuration for monorepo packages"
}
